Workbook

Sheet 00_Cover
B2: Northline Consumer Products
B3: FP&A Monthly Variance Dashboard • FY2026 • $ in thousands
B5: Portfolio sample | All figures are fictional | Built for github.com/saisiri-bandaru/fpna-variance-dashboard
B7: Purpose
B8: This workbook is how an FP&A analyst runs a monthly close flash: compare Actual vs Budget and Actual vs Forecast, explain revenue and margin movement, split OpEx by department, and flag lines that need a conversation with the business. Blue / yellow cells are inputs. Black cells are formulas. Do not paste confidential employer data into a public repo.
B12: Tab map
B13: Tab | C13: What it does
B14: 01_Assumptions | C14: Company setup, close month, and scenario toggles
B15: 02_P&L_Monthly | C15: Revenue, COGS, GP, OpEx, EBITDA by month — Budget / Forecast / Actual
B16: 03_Variance | C16: YTD and latest-month $ and % variances, margin bridges
B17: 04_Dept_OpEx | C17: OpEx by cost center vs budget
B18: 05_Dashboard | C18: One-page view for a standup or ELT pre-read
B19: 06_Data_Dictionary | C19: Field definitions so another analyst can inherit the file
B22: How to refresh after month-end
B23: 1. Set Close Month on 01_Assumptions (yellow cell).
B24: 2. Enter Actuals for that month on 02_P&L_Monthly (yellow cells). Leave future months blank.
B25: 3. If the reforecast changed, update Forecast inputs on the same sheet.
B26: 4. Read 05_Dashboard. Use 03_Variance for the narrative (price/mix proxy = revenue $ variance; cost = COGS rate vs budget).

Sheet 01_Assumptions
B2: Assumptions & control panel
B4: Company | C4: Northline Consumer Products (fictional)
B5: Fiscal year | C5: 2026
B6: Reporting unit | C6: $ thousands
B7: Close month (1=Jan … 12=Dec) | C7: 7 | D7: Sample file is closed through July.
B8: Close month name | C8: =INDEX({"Jan","Feb","Mar","Apr","May","Jun","Jul","Aug","Sep","Oct","Nov","Dec"},C7) -> Jul
B9: YTD months | C9: =C7 -> 7
B11: Color key
B12: Input (edit) | C12: 123 | D12: Blue font + yellow fill
B13: Formula | C13: calculated | D13: Black font — do not overwrite
B15: Budget cost rates (of revenue)
B16: Budget COGS % | C16: 0.6 | D16: Used as the standard cost rate for the COGS rate variance
B17: Budget OpEx % | C17: 0.22
B18: Target GP % | C18: =1-C16 -> 0.4
B20: Notes
B21: Actuals exist for Jan–Jul. Aug–Dec actual cells are blank on purpose so you can practice a close. Forecast is a mid-year reforecast (slightly higher volume, slightly worse COGS rate — a common manufacturing / CPG pattern). Department splits on 04_Dept_OpEx use fixed weights of total OpEx for the sample; replace with a real mapping table in a live model.

Sheet 02_P&L_Monthly
A1: Monthly P&L • $ thousands • inputs in yellow
A2: ="Close month: "&TEXT(01_Assumptions!C7,"0")&" ("&01_Assumptions!C8&")" -> Close month: 7 (Jul)
A4: Line | B4: Case | C4: Jan | D4: Feb | E4: Mar | F4: Apr | G4: May | H4: Jun | I4: Jul | J4: Aug | K4: Sep | L4: Oct | M4: Nov | N4: Dec | O4: FY
A5: Revenue | B5: Budget | C5: 4200 | D5: 4150 | E5: 4380 | F5: 4520 | G5: 4680 | H5: 4900 | I5: 5050 | J5: 5120 | K5: 4980 | L5: 5200 | M5: 5450 | N5: 5720 | O5: =SUM(C5:N5) -> 58350
A6: Revenue | B6: Forecast | C6: 4180 | D6: 4120 | E6: 4410 | F6: 4490 | G6: 4710 | H6: 5020 | I6: 5180 | J6: 5240 | K6: 5100 | L6: 5350 | M6: 5600 | N6: 5880 | O6: =SUM(C6:N6) -> 59280
A7: Revenue | B7: Actual | C7: 4165 | D7: 4098 | E7: 4442 | F7: 4475 | G7: 4738 | H7: 5088 | I7: 5210 | O7: =SUM(C7:N7) -> 32216
A8: COGS | B8: Budget | C8: 2520 | D8: 2490 | E8: 2628 | F8: 2712 | G8: 2808 | H8: 2940 | I8: 3030 | J8: 3072 | K8: 2988 | L8: 3120 | M8: 3270 | N8: 3432 | O8: =SUM(C8:N8) -> 35010
A9: COGS | B9: Forecast | C9: 2550 | D9: 2515 | E9: 2680 | F9: 2740 | G9: 2860 | H9: 3060 | I9: 3140 | J9: 3180 | K9: 3090 | L9: 3240 | M9: 3380 | N9: 3550 | O9: =SUM(C9:N9) -> 35985
A10: COGS | B10: Actual | C10: 2578 | D10: 2532 | E10: 2710 | F10: 2765 | G10: 2895 | H10: 3122 | I10: 3188 | O10: =SUM(C10:N10) -> 19790
A11: Gross profit | B11: Budget | C11: =C5-C8 -> 1680 | D11: =D5-D8 -> 1660 | E11: =E5-E8 -> 1752 | F11: =F5-F8 -> 1808 | G11: =G5-G8 -> 1872 | H11: =H5-H8 -> 1960 | I11: =I5-I8 -> 2020 | J11: =J5-J8 -> 2048 | ... O11: =O5-O8 -> 23340
A12: Gross profit | B12: Forecast | C12: =C6-C9 -> 1630 | D12: =D6-D9 -> 1605 | E12: =E6-E9 -> 1730 | F12: =F6-F9 -> 1750 | G12: =G6-G9 -> 1850 | H12: =H6-H9 -> 1960 | I12: =I6-I9 -> 2040 | J12: =J6-J9 -> 2060 | ... O12: =O6-O9 -> 23295
A13: Gross profit | B13: Actual | C13: =C7-C10 -> 1587 | D13: =D7-D10 -> 1566 | E13: =E7-E10 -> 1732 | F13: =F7-F10 -> 1710 | G13: =G7-G10 -> 1843 | H13: =H7-H10 -> 1966 | I13: =I7-I10 -> 2022 | J13: =J7-J10 -> 0 | ... O13: =O7-O10 -> 12426
A14: OpEx | B14: Budget | C14: 980 | D14: 970 | E14: 990 | F14: 1005 | G14: 1020 | H14: 1040 | I14: 1055 | J14: 1060 | K14: 1045 | L14: 1070 | M14: 1100 | N14: 1140 | O14: =SUM(C14:N14) -> 12475
A15: OpEx | B15: Forecast | C15: 990 | D15: 985 | E15: 1005 | F15: 1010 | G15: 1035 | H15: 1060 | I15: 1075 | J15: 1080 | K15: 1065 | L15: 1090 | M15: 1125 | N15: 1160 | O15: =SUM(C15:N15) -> 12680
A16: OpEx | B16: Actual | C16: 1002 | D16: 978 | E16: 1018 | F16: 1024 | G16: 1048 | H16: 1072 | I16: 1090 | O16: =SUM(C16:N16) -> 7232
A17: EBITDA | B17: Budget | C17: =C11-C14 -> 700 | D17: =D11-D14 -> 690 | E17: =E11-E14 -> 762 | F17: =F11-F14 -> 803 | G17: =G11-G14 -> 852 | H17: =H11-H14 -> 920 | I17: =I11-I14 -> 965 | J17: =J11-J14 -> 988 | ... O17: =O11-O14 -> 10865
A18: EBITDA | B18: Forecast | C18: =C12-C15 -> 640 | D18: =D12-D15 -> 620 | E18: =E12-E15 -> 725 | F18: =F12-F15 -> 740 | G18: =G12-G15 -> 815 | H18: =H12-H15 -> 900 | I18: =I12-I15 -> 965 | J18: =J12-J15 -> 980 | ... O18: =O12-O15 -> 10615
A19: EBITDA | B19: Actual | C19: =C13-C16 -> 585 | D19: =D13-D16 -> 588 | E19: =E13-E16 -> 714 | F19: =F13-F16 -> 686 | G19: =G13-G16 -> 795 | H19: =H13-H16 -> 894 | I19: =I13-I16 -> 932 | J19: =J13-J16 -> 0 | ... O19: =O13-O16 -> 5194
A20: GP % | B20: Budget | C20: =IF(OR(C5="",C5=0),"",C11/C5) -> 0.4 | D20: =IF(OR(D5="",D5=0),"",D11/D5) -> 0.4 | E20: =IF(OR(E5="",E5=0),"",E11/E5) -> 0.4 | F20: =IF(OR(F5="",F5=0),"",F11/F5) -> 0.4 | G20: =IF(OR(G5="",G5=0),"",G11/G5) -> 0.4 | H20: =IF(OR(H5="",H5=0),"",H11/H5) -> 0.4 | I20: =IF(OR(I5="",I5=0),"",I11/I5) -> 0.4 | J20: =IF(OR(J5="",J5=0),"",J11/J5) -> 0.4 | ... O20: =IF(OR(O5="",O5=0),"",O11/O5) -> 0.4
A21: GP % | B21: Forecast | C21: =IF(OR(C6="",C6=0),"",C12/C6) -> 0.38995215 | D21: =IF(OR(D6="",D6=0),"",D12/D6) -> 0.38956311 | E21: =IF(OR(E6="",E6=0),"",E12/E6) -> 0.39229025 | F21: =IF(OR(F6="",F6=0),"",F12/F6) -> 0.38975501 | G21: =IF(OR(G6="",G6=0),"",G12/G6) -> 0.39278132 | H21: =IF(OR(H6="",H6=0),"",H12/H6) -> 0.39043825 | I21: =IF(OR(I6="",I6=0),"",I12/I6) -> 0.39382239 | J21: =IF(OR(J6="",J6=0),"",J12/J6) -> 0.39312977 | ... O21: =IF(OR(O6="",O6=0),"",O12/O6) -> 0.39296559
A22: GP % | B22: Actual | C22: =IF(OR(C7="",C7=0),"",C13/C7) -> 0.38103241 | D22: =IF(OR(D7="",D7=0),"",D13/D7) -> 0.38213763 | E22: =IF(OR(E7="",E7=0),"",E13/E7) -> 0.38991445 | F22: =IF(OR(F7="",F7=0),"",F13/F7) -> 0.38212291 | G22: =IF(OR(G7="",G7=0),"",G13/G7) -> 0.38898269 | H22: =IF(OR(H7="",H7=0),"",H13/H7) -> 0.38639937 | I22: =IF(OR(I7="",I7=0),"",I13/I7) -> 0.38809981 | J22: =IF(OR(J7="",J7=0),"",J13/J7) | ... O22: =IF(OR(O7="",O7=0),"",O13/O7) -> 0.38570896
A23: COGS % | B23: Budget | C23: =IF(OR(C5="",C5=0),"",C8/C5) -> 0.6 | D23: =IF(OR(D5="",D5=0),"",D8/D5) -> 0.6 | E23: =IF(OR(E5="",E5=0),"",E8/E5) -> 0.6 | F23: =IF(OR(F5="",F5=0),"",F8/F5) -> 0.6 | G23: =IF(OR(G5="",G5=0),"",G8/G5) -> 0.6 | H23: =IF(OR(H5="",H5=0),"",H8/H5) -> 0.6 | I23: =IF(OR(I5="",I5=0),"",I8/I5) -> 0.6 | J23: =IF(OR(J5="",J5=0),"",J8/J5) -> 0.6 | ... O23: =IF(OR(O5="",O5=0),"",O8/O5) -> 0.6
A24: COGS % | B24: Forecast | C24: =IF(OR(C6="",C6=0),"",C9/C6) -> 0.61004785 | D24: =IF(OR(D6="",D6=0),"",D9/D6) -> 0.61043689 | E24: =IF(OR(E6="",E6=0),"",E9/E6) -> 0.60770975 | F24: =IF(OR(F6="",F6=0),"",F9/F6) -> 0.61024499 | G24: =IF(OR(G6="",G6=0),"",G9/G6) -> 0.60721868 | H24: =IF(OR(H6="",H6=0),"",H9/H6) -> 0.60956175 | I24: =IF(OR(I6="",I6=0),"",I9/I6) -> 0.60617761 | J24: =IF(OR(J6="",J6=0),"",J9/J6) -> 0.60687023 | ... O24: =IF(OR(O6="",O6=0),"",O9/O6) -> 0.60703441
A25: COGS % | B25: Actual | C25: =IF(OR(C7="",C7=0),"",C10/C7) -> 0.61896759 | D25: =IF(OR(D7="",D7=0),"",D10/D7) -> 0.61786237 | E25: =IF(OR(E7="",E7=0),"",E10/E7) -> 0.61008555 | F25: =IF(OR(F7="",F7=0),"",F10/F7) -> 0.61787709 | G25: =IF(OR(G7="",G7=0),"",G10/G7) -> 0.61101731 | H25: =IF(OR(H7="",H7=0),"",H10/H7) -> 0.61360063 | I25: =IF(OR(I7="",I7=0),"",I10/I7) -> 0.61190019 | J25: =IF(OR(J7="",J7=0),"",J10/J7) | ... O25: =IF(OR(O7="",O7=0),"",O10/O7) -> 0.61429104
A27: Favorable / unfavorable convention: for Revenue, GP, EBITDA a positive Actual−Budget is favorable. For COGS and OpEx a positive Actual−Budget is unfavorable (higher cost).

Sheet 03_Variance
A1: Variance analysis
A2: YTD uses months 1 through Close Month. Latest month = Close Month. $ thousands.
A4: YTD flash
A5: Line | B5: YTD Actual | C5: YTD Budget | D5: YTD Forecast | E5: Act vs Bud $ | F5: Act vs Bud % | G5: Act vs Fcst $
A6: Revenue | B6: =SUMPRODUCT(('02_P&L_Monthly'!C7:N7)*(COLUMN('02_P&L_Monthly'!C7:N7)-COLUMN('02_P&L_Monthly'!C7)+1<=01_Assumptions!$C$7)) -> 32216 | C6: =SUMPRODUCT(('02_P&L_Monthly'!C5:N5)*(COLUMN('02_P&L_Monthly'!C5:N5)-COLUMN('02_P&L_Monthly'!C5)+1<=01_Assumptions!$C$7)) -> 31880 | D6: =SUMPRODUCT(('02_P&L_Monthly'!C6:N6)*(COLUMN('02_P&L_Monthly'!C6:N6)-COLUMN('02_P&L_Monthly'!C6)+1<=01_Assumptions!$C$7)) -> 32110 | E6: =B6-C6 -> 336 | F6: =IF(C6=0,NA(),E6/C6) -> 0.010539523 | G6: =B6-D6 -> 106
A7: COGS | B7: =SUMPRODUCT(('02_P&L_Monthly'!C10:N10)*(COLUMN('02_P&L_Monthly'!C10:N10)-COLUMN('02_P&L_Monthly'!C10)+1<=01_Assumptions!$C$7)) -> 19790 | C7: =SUMPRODUCT(('02_P&L_Monthly'!C8:N8)*(COLUMN('02_P&L_Monthly'!C8:N8)-COLUMN('02_P&L_Monthly'!C8)+1<=01_Assumptions!$C$7)) -> 19128 | D7: =SUMPRODUCT(('02_P&L_Monthly'!C9:N9)*(COLUMN('02_P&L_Monthly'!C9:N9)-COLUMN('02_P&L_Monthly'!C9)+1<=01_Assumptions!$C$7)) -> 19545 | E7: =B7-C7 -> 662 | F7: =IF(C7=0,NA(),E7/C7) -> 0.03460895 | G7: =B7-D7 -> 245
A8: Gross profit | B8: =SUMPRODUCT(('02_P&L_Monthly'!C13:N13)*(COLUMN('02_P&L_Monthly'!C13:N13)-COLUMN('02_P&L_Monthly'!C13)+1<=01_Assumptions!$C$7)) -> 12426 | C8: =SUMPRODUCT(('02_P&L_Monthly'!C11:N11)*(COLUMN('02_P&L_Monthly'!C11:N11)-COLUMN('02_P&L_Monthly'!C11)+1<=01_Assumptions!$C$7)) -> 12752 | D8: =SUMPRODUCT(('02_P&L_Monthly'!C12:N12)*(COLUMN('02_P&L_Monthly'!C12:N12)-COLUMN('02_P&L_Monthly'!C12)+1<=01_Assumptions!$C$7)) -> 12565 | E8: =B8-C8 -> -326 | F8: =IF(C8=0,NA(),E8/C8) -> -0.025564617 | G8: =B8-D8 -> -139
A9: OpEx | B9: =SUMPRODUCT(('02_P&L_Monthly'!C16:N16)*(COLUMN('02_P&L_Monthly'!C16:N16)-COLUMN('02_P&L_Monthly'!C16)+1<=01_Assumptions!$C$7)) -> 7232 | C9: =SUMPRODUCT(('02_P&L_Monthly'!C14:N14)*(COLUMN('02_P&L_Monthly'!C14:N14)-COLUMN('02_P&L_Monthly'!C14)+1<=01_Assumptions!$C$7)) -> 7060 | D9: =SUMPRODUCT(('02_P&L_Monthly'!C15:N15)*(COLUMN('02_P&L_Monthly'!C15:N15)-COLUMN('02_P&L_Monthly'!C15)+1<=01_Assumptions!$C$7)) -> 7160 | E9: =B9-C9 -> 172 | F9: =IF(C9=0,NA(),E9/C9) -> 0.024362606 | G9: =B9-D9 -> 72
A10: EBITDA | B10: =SUMPRODUCT(('02_P&L_Monthly'!C19:N19)*(COLUMN('02_P&L_Monthly'!C19:N19)-COLUMN('02_P&L_Monthly'!C19)+1<=01_Assumptions!$C$7)) -> 5194 | C10: =SUMPRODUCT(('02_P&L_Monthly'!C17:N17)*(COLUMN('02_P&L_Monthly'!C17:N17)-COLUMN('02_P&L_Monthly'!C17)+1<=01_Assumptions!$C$7)) -> 5692 | D10: =SUMPRODUCT(('02_P&L_Monthly'!C18:N18)*(COLUMN('02_P&L_Monthly'!C18:N18)-COLUMN('02_P&L_Monthly'!C18)+1<=01_Assumptions!$C$7)) -> 5405 | E10: =B10-C10 -> -498 | F10: =IF(C10=0,NA(),E10/C10) -> -0.087491216 | G10: =B10-D10 -> -211
A12: Latest closed month
A13: Line | B13: Actual | C13: Budget | D13: Forecast | E13: Act vs Bud $ | F13: Act vs Bud % | G13: Act vs Fcst $
A14: Revenue | B14: =INDEX('02_P&L_Monthly'!C7:N7,01_Assumptions!$C$7) -> 5210 | C14: =INDEX('02_P&L_Monthly'!C5:N5,01_Assumptions!$C$7) -> 5050 | D14: =INDEX('02_P&L_Monthly'!C6:N6,01_Assumptions!$C$7) -> 5180 | E14: =B14-C14 -> 160 | F14: =IF(C14=0,NA(),E14/C14) -> 0.031683168 | G14: =B14-D14 -> 30
A15: COGS | B15: =INDEX('02_P&L_Monthly'!C10:N10,01_Assumptions!$C$7) -> 3188 | C15: =INDEX('02_P&L_Monthly'!C8:N8,01_Assumptions!$C$7) -> 3030 | D15: =INDEX('02_P&L_Monthly'!C9:N9,01_Assumptions!$C$7) -> 3140 | E15: =B15-C15 -> 158 | F15: =IF(C15=0,NA(),E15/C15) -> 0.052145215 | G15: =B15-D15 -> 48
A16: Gross profit | B16: =INDEX('02_P&L_Monthly'!C13:N13,01_Assumptions!$C$7) -> 2022 | C16: =INDEX('02_P&L_Monthly'!C11:N11,01_Assumptions!$C$7) -> 2020 | D16: =INDEX('02_P&L_Monthly'!C12:N12,01_Assumptions!$C$7) -> 2040 | E16: =B16-C16 -> 2 | F16: =IF(C16=0,NA(),E16/C16) -> 0.00099009901 | G16: =B16-D16 -> -18
A17: OpEx | B17: =INDEX('02_P&L_Monthly'!C16:N16,01_Assumptions!$C$7) -> 1090 | C17: =INDEX('02_P&L_Monthly'!C14:N14,01_Assumptions!$C$7) -> 1055 | D17: =INDEX('02_P&L_Monthly'!C15:N15,01_Assumptions!$C$7) -> 1075 | E17: =B17-C17 -> 35 | F17: =IF(C17=0,NA(),E17/C17) -> 0.033175355 | G17: =B17-D17 -> 15
A18: EBITDA | B18: =INDEX('02_P&L_Monthly'!C19:N19,01_Assumptions!$C$7) -> 932 | C18: =INDEX('02_P&L_Monthly'!C17:N17,01_Assumptions!$C$7) -> 965 | D18: =INDEX('02_P&L_Monthly'!C18:N18,01_Assumptions!$C$7) -> 965 | E18: =B18-C18 -> -33 | F18: =IF(C18=0,NA(),E18/C18) -> -0.034196891 | G18: =B18-D18 -> -33
A21: COGS rate bridge (cost accounting lens)
A22: YTD actual COGS % | B22: =IF(B6=0,NA(),B7/B6) -> 0.61429104
A23: YTD budget COGS % | B23: =IF(C6=0,NA(),C7/C6) -> 0.6
A24: Rate variance $ (actual sales × rate gap) | B24: =B6*(B22-B23) -> 460.4 | C24: Positive = costs ran hotter than standard — investigate yield, freight, mix, or standard cost updates
A25: Volume / activity $ on COGS (budget rate × sales gap) | B25: =(B6-C6)*B23 -> 201.6
A26: Check: rate $ + volume $ should tie to total COGS $ variance | B26: =B24+B25 -> 662 | C26: =B7-C7 -> 662 | D26: Tie-out (should match B26)
A28: Suggested close narrative (edit after you read the numbers)
A29: YTD revenue is slightly ahead of budget on stronger mid-year volume. Gross margin is the watch-item: COGS % is running above the 60% standard, so most of the COGS dollar miss is rate, not volume. That is the conversation with operations (scrap, mix into lower-margin SKUs, inbound freight). OpEx is close to budget; EBITDA follows the margin gap more than the spending gap.

Sheet 04_Dept_OpEx
A1: OpEx by department • $ thousands
A2: Department weights are sample planning rates. Replace with your mapping table for a live close.
A4: Department | B4: Weight | C4: YTD Actual | D4: YTD Budget | E4: Var $ | F4: Var %
A5: Sales & Marketing | B5: 0.38 | C5: =$C$12*B5 -> 2748.16 | D5: =$D$12*B5 -> 2682.8 | E5: =C5-D5 -> 65.36 | F5: =IF(D5=0,NA(),E5/D5) -> 0.024362606
A6: Operations | B6: 0.22 | C6: =$C$12*B6 -> 1591.04 | D6: =$D$12*B6 -> 1553.2 | E6: =C6-D6 -> 37.84 | F6: =IF(D6=0,NA(),E6/D6) -> 0.024362606
A7: G&A | B7: 0.18 | C7: =$C$12*B7 -> 1301.76 | D7: =$D$12*B7 -> 1270.8 | E7: =C7-D7 -> 30.96 | F7: =IF(D7=0,NA(),E7/D7) -> 0.024362606
A8: Finance | B8: 0.09 | C8: =$C$12*B8 -> 650.88 | D8: =$D$12*B8 -> 635.4 | E8: =C8-D8 -> 15.48 | F8: =IF(D8=0,NA(),E8/D8) -> 0.024362606
A9: IT | B9: 0.08 | C9: =$C$12*B9 -> 578.56 | D9: =$D$12*B9 -> 564.8 | E9: =C9-D9 -> 13.76 | F9: =IF(D9=0,NA(),E9/D9) -> 0.024362606
A10: HR | B10: 0.05 | C10: =$C$12*B10 -> 361.6 | D10: =$D$12*B10 -> 353 | E10: =C10-D10 -> 8.6 | F10: =IF(D10=0,NA(),E10/D10) -> 0.024362606
A11: Control totals (must = 100% / YTD OpEx) | B11: =SUM(B5:B10) -> 1 | C11: =SUM(C5:C10) -> 7232 | D11: =SUM(D5:D10) -> 7060
A12: YTD Actual OpEx | C12: =SUMPRODUCT(('02_P&L_Monthly'!C16:N16)*(COLUMN('02_P&L_Monthly'!C16:N16)-COLUMN('02_P&L_Monthly'!C16)+1<=01_Assumptions!$C$7)) -> 7232 | D12: =SUMPRODUCT(('02_P&L_Monthly'!C14:N14)*(COLUMN('02_P&L_Monthly'!C14:N14)-COLUMN('02_P&L_Monthly'!C14)+1<=01_Assumptions!$C$7)) -> 7060
A13: YTD Budget OpEx
A15: Note: this sample applies the same weight to actual and budget so department variances only appear if you change a weight or hook departments to real actuals. That is intentional — it shows the structure without fake precision.

Sheet 05_Dashboard
B2: FY2026 FP&A flash
B3: =01_Assumptions!C4 -> Northline Consumer Products (fictional)
B4: ="YTD through "&01_Assumptions!C8&" | $ thousands" -> YTD through Jul | $ thousands
B6: YTD Revenue | D6: YTD Gross profit | F6: YTD EBITDA | H6: YTD COGS %
B7: =03_Variance!B6 -> 32216 | D7: =03_Variance!B8 -> 12426 | F7: =03_Variance!B10 -> 5194 | H7: =03_Variance!B22 -> 0.61429104
B8: =03_Variance!E6 -> 336 | D8: =03_Variance!E8 -> -326 | F8: =03_Variance!E10 -> -498 | H8: =03_Variance!B22-03_Variance!B23 -> 0.014291036
B9: variance vs budget | D9: variance vs budget | F9: variance vs budget | H9: variance vs budget
B11: Monthly revenue — Budget vs Forecast vs Actual
B13: Month | C13: Jan | D13: Feb | E13: Mar | F13: Apr | G13: May | H13: Jun | I13: Jul | J13: Aug | K13: Sep | L13: Oct | M13: Nov | N13: Dec
B14: Budget | C14: ='02_P&L_Monthly'!C5 -> 4200 | D14: ='02_P&L_Monthly'!D5 -> 4150 | E14: ='02_P&L_Monthly'!E5 -> 4380 | F14: ='02_P&L_Monthly'!F5 -> 4520 | G14: ='02_P&L_Monthly'!G5 -> 4680 | H14: ='02_P&L_Monthly'!H5 -> 4900 | I14: ='02_P&L_Monthly'!I5 -> 5050 | J14: ='02_P&L_Monthly'!J5 -> 5120 | ... N14: ='02_P&L_Monthly'!N5 -> 5720
B15: Forecast | C15: ='02_P&L_Monthly'!C6 -> 4180 | D15: ='02_P&L_Monthly'!D6 -> 4120 | E15: ='02_P&L_Monthly'!E6 -> 4410 | F15: ='02_P&L_Monthly'!F6 -> 4490 | G15: ='02_P&L_Monthly'!G6 -> 4710 | H15: ='02_P&L_Monthly'!H6 -> 5020 | I15: ='02_P&L_Monthly'!I6 -> 5180 | J15: ='02_P&L_Monthly'!J6 -> 5240 | ... N15: ='02_P&L_Monthly'!N6 -> 5880
B16: Actual | C16: ='02_P&L_Monthly'!C7 -> 4165 | D16: ='02_P&L_Monthly'!D7 -> 4098 | E16: ='02_P&L_Monthly'!E7 -> 4442 | F16: ='02_P&L_Monthly'!F7 -> 4475 | G16: ='02_P&L_Monthly'!G7 -> 4738 | H16: ='02_P&L_Monthly'!H7 -> 5088 | I16: ='02_P&L_Monthly'!I7 -> 5210 | J16: ='02_P&L_Monthly'!J7 -> 0 | ... N16: ='02_P&L_Monthly'!N7 -> 0
B32: What an interviewer should see
B33: You can run a monthly flash without a planning system: inputs stay isolated, variances are signed correctly for cost vs revenue, and COGS is split into rate vs volume so the operations conversation is specific. Swap the yellow cells for any company and the dashboard still holds.

Sheet 06_Data_Dictionary
A1: Data dictionary
A3: Field | B3: Definition | C3: Source in file
A4: Close month | B4: Last month with a complete actual close (1–12). | C4: 01_Assumptions!C7
A5: Budget | B5: Board / AOP plan locked before the year. | C5: 02_P&L_Monthly Budget rows
A6: Forecast | B6: Latest rolling reforecast (sample = mid-year). | C6: 02_P&L_Monthly Forecast rows
A7: Actual | B7: Books after close. Future months left blank. | C7: 02_P&L_Monthly Actual rows
A8: Act vs Bud $ | B8: Actual − Budget. For cost lines, positive means overspend. | C8: 03_Variance
A9: COGS rate variance | B9: Actual sales × (actual COGS% − budget COGS%). | C9: 03_Variance!B24
A10: COGS volume variance | B10: Budget COGS% × (actual sales − budget sales). | C10: 03_Variance!B25
A11: Department weight | B11: Planning mix of OpEx. Not a real GL map. | C11: 04_Dept_OpEx!B5:B10
A12: Unit | B12: All money figures are $ thousands unless a % is labeled. | C12: Cover / Assumptions
